pyoncokb/__init__.py
pyoncokb/annotations/__init__.py
pyoncokb/annotations/batchannotator.py
pyoncokb/annotations/cameltosnakecasekeyconverter.py
pyoncokb/annotations/copynumberalterationannotator.py
pyoncokb/annotations/genomicchangeannotator.py
pyoncokb/annotations/proteinchangeannotator.py
pyoncokb/annotations/proteinchangesannotator.py
pyoncokb/annotations/structuralvariantannotator.py
pyoncokb/cancergenes/__init__.py
pyoncokb/cancergenes/cancergenefieldnameconverter.py
pyoncokb/cancergenes/cancergenelistget.py
pyoncokb/models/__init__.py
pyoncokb/models/articleabstract.py
pyoncokb/models/cancergene.py
pyoncokb/models/citations.py
pyoncokb/models/drug.py
pyoncokb/models/implication.py
pyoncokb/models/indicatorqueryresp.py
pyoncokb/models/indicatorquerytreatment.py
pyoncokb/models/levelofevidence.py
pyoncokb/models/mutationeffectresp.py
pyoncokb/models/query.py
pyoncokb/models/referencegenome.py
pyoncokb/models/svtype.py
pyoncokb/models/tumorform.py
pyoncokb/models/tumortype.py
pyoncokb/oncokbapi/__init__.py
pyoncokb/oncokbapi/oncokbapi.py
tests/__init__.py
tests/testconfig.py
tests/annotations/__init__.py
tests/annotations/test_cameltosnakecasekeyconverter.py
tests/annotations/test_proteinchangesannotator.py
tests/annotations/copynumberalterationannotator/__init__.py
tests/annotations/copynumberalterationannotator/test_erbb2_amplification.py
tests/annotations/copynumberalterationannotator/test_erbb2_gain.py
tests/annotations/copynumberalterationannotator/test_met_amplification.py
tests/annotations/copynumberalterationannotator/test_met_gain.py
tests/annotations/copynumberalterationannotator/test_mycn_amplification.py
tests/annotations/copynumberalterationannotator/test_mycn_gain.py
tests/annotations/copynumberalterationannotator/test_oncokb_api_count_and_sleep.py
tests/annotations/copynumberalterationannotator/test_rb1_deletion.py
tests/annotations/copynumberalterationannotator/test_rb1_loss.py
tests/annotations/genomicchangeannotator/__init__.py
pyoncokb-0.0.3.dist-info/METADATA
pyoncokb-0.0.3.dist-info/WHEEL
pyoncokb-0.0.3.dist-info/top_level.txt
pyoncokb-0.0.3.dist-info/RECORD
