Metadata-Version: 2.1
Name: pyoncokb
Version: 0.0.3
Summary: A simple package for OncoKB API
Home-page: https://github.com/markgene/pyoncokb
Author: Mark J Chen
Author-email: mjchen.gene@gmail.com
Classifier: Programming Language :: Python :: 3
Classifier: License :: OSI Approved :: MIT License
Classifier: Operating System :: OS Independent
Requires-Python: >=3.6
Requires-Dist: dacite
Requires-Dist: requests
